nwd/__init__.py
nwd/__main__.py
nwd/daemon.py
nwd/desktop.py
nwd/email.py
nwd/gtk.py
nwd/notify.py
nwd/osx.py
nwd/tabular.py
nwd/term.py
nwd/windows.py
nwd-2.1.0.dist-info/LICENSE
nwd-2.1.0.dist-info/METADATA
nwd-2.1.0.dist-info/WHEEL
nwd-2.1.0.dist-info/entry_points.txt
nwd-2.1.0.dist-info/top_level.txt
nwd-2.1.0.dist-info/RECORD
