Metadata-Version: 2.1
Name: nwd
Version: 2.1.0
Summary: Notify When Done (NWD). A tool for posting a desktop notification, E-mail, or other alert when a process finishes.
Home-page: https://github.com/ESultanik/nwd
Author: Evan Sultanik
License: UNKNOWN
Platform: UNKNOWN
Classifier: Development Status :: 5 - Production/Stable
Classifier: Environment :: Console
Classifier: Environment :: MacOS X
Classifier: Environment :: Win32 (MS Windows)
Classifier: Environment :: X11 Applications :: GTK
Classifier: Intended Audience :: Developers
Classifier: Intended Audience :: End Users/Desktop
Classifier: License :: OSI Approved :: GNU Affero General Public License v3
Classifier: Topic :: System :: Monitoring
Classifier: Topic :: Utilities
Requires-Python: >=3.6
Requires-Dist: keyring
Requires-Dist: psutil
Requires-Dist: pyobjc ; platform_system == "Darwin"
Requires-Dist: win10toast ; platform_system == "Windows"
Provides-Extra: dev
Requires-Dist: flake8 ; extra == 'dev'
